[
  {
    "ContainingType": "PersonApi.Controllers.PersonController",
    "Method": "GetAllPersons",
    "RelativePath": "api/Person",
    "HttpMethod": "GET",
    "IsController": true,
    "Order": 0,
    "Parameters": [],
    "ReturnTypes": [
      {
        "Type": "System.Collections.Generic.IEnumerable\u00601[[PersonApi.Protos.Person, PersonApi, Version=1.0.0.0, Culture=neutral, PublicKeyToken=null]]",
        "MediaTypes": [
          "text/plain",
          "application/json",
          "text/json"
        ],
        "StatusCode": 200
      }
    ]
  },
  {
    "ContainingType": "PersonApi.Controllers.PersonController",
    "Method": "CreatePerson",
    "RelativePath": "api/Person",
    "HttpMethod": "POST",
    "IsController": true,
    "Order": 0,
    "Parameters": [
      {
        "Name": "proto",
        "Type": "PersonApi.Protos.Person",
        "IsRequired": true
      }
    ],
    "ReturnTypes": [
      {
        "Type": "PersonApi.Protos.Person",
        "MediaTypes": [
          "text/plain",
          "application/json",
          "text/json"
        ],
        "StatusCode": 200
      }
    ]
  },
  {
    "ContainingType": "PersonApi.Controllers.PersonController",
    "Method": "GetPerson",
    "RelativePath": "api/Person/{id}",
    "HttpMethod": "GET",
    "IsController": true,
    "Order": 0,
    "Parameters": [
      {
        "Name": "id",
        "Type": "System.Int32",
        "IsRequired": true
      }
    ],
    "ReturnTypes": [
      {
        "Type": "PersonApi.Protos.Person",
        "MediaTypes": [
          "text/plain",
          "application/json",
          "text/json"
        ],
        "StatusCode": 200
      }
    ]
  },
  {
    "ContainingType": "PersonApi.Controllers.PersonController",
    "Method": "UpdatePerson",
    "RelativePath": "api/Person/{id}",
    "HttpMethod": "PUT",
    "IsController": true,
    "Order": 0,
    "Parameters": [
      {
        "Name": "id",
        "Type": "System.Int32",
        "IsRequired": true
      },
      {
        "Name": "proto",
        "Type": "PersonApi.Protos.Person",
        "IsRequired": true
      }
    ],
    "ReturnTypes": []
  },
  {
    "ContainingType": "PersonApi.Controllers.PersonController",
    "Method": "DeletePerson",
    "RelativePath": "api/Person/{id}",
    "HttpMethod": "DELETE",
    "IsController": true,
    "Order": 0,
    "Parameters": [
      {
        "Name": "id",
        "Type": "System.Int32",
        "IsRequired": true
      }
    ],
    "ReturnTypes": []
  }
]